livekit/rtc/__init__.py
livekit/rtc/_ffi_client.py
livekit/rtc/_utils.py
livekit/rtc/apm.py
livekit/rtc/audio_filter.py
livekit/rtc/audio_frame.py
livekit/rtc/audio_mixer.py
livekit/rtc/audio_resampler.py
livekit/rtc/audio_source.py
livekit/rtc/audio_stream.py
livekit/rtc/data_stream.py
livekit/rtc/e2ee.py
livekit/rtc/event_emitter.py
livekit/rtc/frame_processor.py
livekit/rtc/jupyter.py
livekit/rtc/log.py
livekit/rtc/media_devices.py
livekit/rtc/participant.py
livekit/rtc/py.typed
livekit/rtc/room.py
livekit/rtc/rpc.py
livekit/rtc/synchronizer.py
livekit/rtc/track.py
livekit/rtc/track_publication.py
livekit/rtc/transcription.py
livekit/rtc/utils.py
livekit/rtc/version.py
livekit/rtc/video_frame.py
livekit/rtc/video_source.py
livekit/rtc/video_stream.py
livekit/rtc/_proto/__init__.py
livekit/rtc/_proto/audio_frame_pb2.py
livekit/rtc/_proto/audio_frame_pb2.pyi
livekit/rtc/_proto/data_stream_pb2.py
livekit/rtc/_proto/data_stream_pb2.pyi
livekit/rtc/_proto/e2ee_pb2.py
livekit/rtc/_proto/e2ee_pb2.pyi
livekit/rtc/_proto/ffi_pb2.py
livekit/rtc/_proto/ffi_pb2.pyi
livekit/rtc/_proto/handle_pb2.py
livekit/rtc/_proto/handle_pb2.pyi
livekit/rtc/_proto/participant_pb2.py
livekit/rtc/_proto/participant_pb2.pyi
livekit/rtc/_proto/room_pb2.py
livekit/rtc/_proto/room_pb2.pyi
livekit/rtc/_proto/rpc_pb2.py
livekit/rtc/_proto/rpc_pb2.pyi
livekit/rtc/_proto/stats_pb2.py
livekit/rtc/_proto/stats_pb2.pyi
livekit/rtc/_proto/track_pb2.py
livekit/rtc/_proto/track_pb2.pyi
livekit/rtc/_proto/track_publication_pb2.py
livekit/rtc/_proto/track_publication_pb2.pyi
livekit/rtc/_proto/video_frame_pb2.py
livekit/rtc/_proto/video_frame_pb2.pyi
livekit/rtc/resources/LICENSE.md
livekit/rtc/resources/__init__.py
livekit/rtc/resources/liblivekit_ffi.so
livekit/rtc/resources/livekit_ffi.h
livekit/rtc/resources/jupyter-html/index.html
livekit.libs/libblkid-af8b1247.so.1.1.0
livekit.libs/libffi-b23fa0bb.so.6.0.2
livekit-1.0.25.dist-info/METADATA
livekit-1.0.25.dist-info/WHEEL
livekit-1.0.25.dist-info/top_level.txt
livekit-1.0.25.dist-info/RECORD
livekit-1.0.25.dist-info/sboms/auditwheel.cdx.json
