Metadata-Version: 2.4
Name: livekit
Version: 1.0.25
Summary: Python Real-time SDK for LiveKit
Author-email: LiveKit <support@livekit.io>
License-Expression: Apache-2.0
Project-URL: Documentation, https://docs.livekit.io
Project-URL: Website, https://livekit.io/
Project-URL: Source, https://github.com/livekit/python-sdks/
Keywords: webrtc,realtime,audio,video,livekit
Classifier: Intended Audience :: Developers
Classifier: Topic :: Multimedia :: Sound/Audio
Classifier: Topic :: Multimedia :: Video
Classifier: Topic :: Scientific/Engineering :: Artificial Intelligence
Classifier: Programming Language :: Python :: 3
Classifier: Programming Language :: Python :: 3.9
Classifier: Programming Language :: Python :: 3.10
Classifier: Programming Language :: Python :: 3 :: Only
Requires-Python: >=3.9.0
Requires-Dist: protobuf>=4.25.0
Requires-Dist: types-protobuf>=3
Requires-Dist: aiofiles>=24
Requires-Dist: numpy>=1.26
